{
  "artifact": "Xen Executive Documentary",
  "release": "Xen-Centric XFS Finish v1.0",
  "status": "canonical-candidate",
  "authority": "Darren Cureton",
  "xen_is_protagonist": true,
  "client_is_proof_participant": true,
  "scene_count": 9,
  "runtime_controller": "src/ed-premiere-clean-v1.js",
  "finish_layer": [
    "src/xfs-xen-centric-finish-v1.css",
    "src/xfs-xen-centric-finish-v1.js"
  ],
  "institutional_memory": {
    "from": "Marisol",
    "to": "Vianka",
    "preserved_by": "Xen",
    "proof_family": "XBM Suite Version 2.0",
    "canonical_repository": "decureton-xencreator/xen-operating-system"
  },
  "monetization_families": [
    "Institutional Memory Systems",
    "Department Operating Systems",
    "Living Company Operating Layers",
    "Bilingual Publication Systems",
    "Implementation and Managed Optimization",
    "Academy and Certification",
    "Franchise Enablement",
    "Licensing and Recurring Platform Services"
  ],
  "external_gates": [
    "Darren iPhone physical acceptance",
    "custom domain purchase and DNS activation",
    "recorded or approved production narration asset"
  ]
}